azcam_testers/__init__.py
azcam_testers/tools/__init__.py
azcam_testers/tools/basetester.py
azcam_testers/tools/bias.py
azcam_testers/tools/dark.py
azcam_testers/tools/defects.py
azcam_testers/tools/detcal.py
azcam_testers/tools/detchar.py
azcam_testers/tools/eper.py
azcam_testers/tools/fe55.py
azcam_testers/tools/gain.py
azcam_testers/tools/linearity.py
azcam_testers/tools/metrology.py
azcam_testers/tools/pocketpump.py
azcam_testers/tools/prnu.py
azcam_testers/tools/ptc.py
azcam_testers/tools/qe.py
azcam_testers/tools/ramp.py
azcam_testers/tools/report.css
azcam_testers/tools/report.py
azcam_testers/tools/superflat.py
azcam_testers/tools/testers.py
azcam_testers-23.0.dist-info/LICENSE
azcam_testers-23.0.dist-info/WHEEL
azcam_testers-23.0.dist-info/METADATA
azcam_testers-23.0.dist-info/RECORD
