Metadata-Version: 2.1
Name: azcam-testers
Version: 23.0
Summary: Image sensor acquisition and analysis test suite.
Keywords: ccd,imaging,astronomy,sensors
Author: Michael Lesser
Author-email: mlesser@arizona.edu
Requires-Dist: numpy
Requires-Dist: matplotlib
Requires-Dist: astropy
Requires-Dist: pdfkit
Requires-Dist: markdown
Requires-Dist: pypdf
Requires-Dist: azcam-console
Project-URL: Documentation, https://azcam.readthedocs.io/
Project-URL: Repository, https://github.com/mplesser/azcam-testers/
